AUTHORS.rst
CONTRIBUTING.rst
HISTORY.rst
LICENSE
MANIFEST.in
README.rst
setup.cfg
setup.py
docs/Makefile
docs/authors.rst
docs/conf.py
docs/contributing.rst
docs/history.rst
docs/index.rst
docs/installation.rst
docs/make.bat
docs/readme.rst
docs/usage.rst
tests/__init__.py
tests/test_the_movie_api.py
the_movie_api/__init__.py
the_movie_api/the_movie_api.py
the_movie_api.egg-info/PKG-INFO
the_movie_api.egg-info/SOURCES.txt
the_movie_api.egg-info/dependency_links.txt
the_movie_api.egg-info/not-zip-safe
the_movie_api.egg-info/requires.txt
the_movie_api.egg-info/top_level.txt
the_movie_api/utils/__init__.py
the_movie_api/utils/regex_utils.py
the_movie_api/utils/search_utils.py