Metadata-Version: 2.1
Name: the-movie-api
Version: 0.1.1
Summary: Short python class to interact with the movies API
Home-page: https://github.com/paul-armstrong-dev/the_movie_api
Author: Paul Armstrong
Author-email: paul.armstrong211@gmail.com
License: MIT license
Keywords: the_movie_api
Platform: UNKNOWN
Classifier: Development Status :: 2 - Pre-Alpha
Classifier: Intended Audience :: Developers
Classifier: License :: OSI Approved :: MIT License
Classifier: Natural Language :: English
Classifier: Programming Language :: Python :: 3
Classifier: Programming Language :: Python :: 3.6
Classifier: Programming Language :: Python :: 3.7
Classifier: Programming Language :: Python :: 3.8
Requires-Python: >=3.6
License-File: LICENSE
License-File: AUTHORS.rst
